README.rst
aes_keywrap.py
setup.py
aes_keywrap.egg-info/PKG-INFO
aes_keywrap.egg-info/SOURCES.txt
aes_keywrap.egg-info/dependency_links.txt
aes_keywrap.egg-info/top_level.txt