Metadata-Version: 1.0
Name: aes-keywrap
Version: 17.12.1
Summary: UNKNOWN
Home-page: https://github.com/kurtbrose/aes_keywrap
Author: Kurt Rose
Author-email: kurt@kurtrose.com
License: MIT
Platform: UNKNOWN
